rland_py_study/__init__.py
rland_py_study/calculator.py
rland_py_study/serial/__init__.py
rland_py_study/serial/basic.py
rland_py_study-0.0.0.2.dist-info/LICENCE.md
rland_py_study-0.0.0.2.dist-info/METADATA
rland_py_study-0.0.0.2.dist-info/WHEEL
rland_py_study-0.0.0.2.dist-info/top_level.txt
rland_py_study-0.0.0.2.dist-info/RECORD
