Metadata-Version: 2.1
Name: rland-py-study
Version: 0.0.0.2
Summary: Package for studying python features
Home-page: https://github.com/BenzeneKim/rland_py_study
Author: Roboroboland
Author-email: kimjunseob1@roborobo.co.kr
License: UNKNOWN
Platform: UNKNOWN
Classifier: Programming Language :: Python :: 3
Classifier: License :: OSI Approved :: GNU General Public License v3 (GPLv3)
Classifier: Operating System :: OS Independent
Requires-Python: >=3.6
